humanactivity
