Metadata-Version: 1.0
Name: humanactivity
Version: 0.2
Summary: Human activity recognizer based on keras and thensorflow
Home-page: http://github.com/XEOBO/HumanActivity
Author: Vladimir Zbiljic
Author-email: vladimir.zbiljic@gmail.com
License: MIT
Platform: UNKNOWN
